dmarc/models.py
dmarc/urls.py
dmarc/views.py
dmarc/__init__.py
dmarc/admin.py
dmarc/test_import.py
dmarc/management/__init__.py
dmarc/management/commands/__init__.py
dmarc/management/commands/importdmarcreport.py
dmarc/migrations/0001_initial.py
dmarc/migrations/0002_auto_20150303_1606.py
dmarc/migrations/0003_auto_20150307_1531.py
dmarc/migrations/__init__.py
dmarc/migrations/0004_auto_20150310_1725.py
dmarc/migrations/0005_report_report_xml.py
dmarc/templates/dmarc/report.html
django_dmarc-0.1.10.dist-info/top_level.txt
django_dmarc-0.1.10.dist-info/METADATA
django_dmarc-0.1.10.dist-info/DESCRIPTION.rst
django_dmarc-0.1.10.dist-info/metadata.json
django_dmarc-0.1.10.dist-info/WHEEL
django_dmarc-0.1.10.dist-info/RECORD
