Metadata-Version: 2.0
Name: django-dmarc
Version: 0.1.10
Summary: 
